DocExtract/__init__.py
DocExtract/extract_details.py
doc_extract-0.0.1.dist-info/LICENSE
doc_extract-0.0.1.dist-info/METADATA
doc_extract-0.0.1.dist-info/WHEEL
doc_extract-0.0.1.dist-info/top_level.txt
doc_extract-0.0.1.dist-info/RECORD
