Metadata-Version: 2.1
Name: doc-extract
Version: 0.0.1
Summary: Extract information from documents using Cloud APIs and open-source
Home-page: https://github.com/saharmor/DocExtract
Author: Sahar Mor
Author-email: koryoislie@email.COM
License: UNKNOWN
Platform: UNKNOWN
Classifier: Programming Language :: Python :: 3
Classifier: License :: OSI Approved :: MIT License
Classifier: Operating System :: OS Independent
